winerp/__init__.py
winerp/__main__.py
winerp/client.py
winerp/server.py
winerp/lib/errors.py
winerp/lib/events.py
winerp/lib/message.py
winerp/lib/payload.py
winerp-1.5.0.dist-info/LICENSE
winerp-1.5.0.dist-info/METADATA
winerp-1.5.0.dist-info/WHEEL
winerp-1.5.0.dist-info/entry_points.txt
winerp-1.5.0.dist-info/top_level.txt
winerp-1.5.0.dist-info/RECORD
