Metadata-Version: 2.1
Name: winerp
Version: 1.5.0
Summary: Websocket based IPC for discord.py bots
Home-page: https://github.com/nouman0103/winerp
Author: BlackThunder
Author-email: nouman0103@gmail.com
License: MIT
Project-URL: Bug Tracker, https://github.com/nouman0103/winerp/issues
Project-URL: Documentation, https://winerp.readthedocs.io/en/latest/
Classifier: License :: OSI Approved :: MIT License
Classifier: Intended Audience :: Developers
Classifier: Programming Language :: Python :: 3
Classifier: Programming Language :: Python :: 3.6
Classifier: Operating System :: OS Independent
Classifier: Typing :: Typed
Requires-Python: >=3.6
License-File: LICENSE
Requires-Dist: websockets
Requires-Dist: websocket-server
Requires-Dist: orjson
